tracktotrip4/__init__.py
tracktotrip4/classifier.py
tracktotrip4/compression.py
tracktotrip4/kalman.py
tracktotrip4/learn_trip.py
tracktotrip4/location.py
tracktotrip4/point.py
tracktotrip4/segment.py
tracktotrip4/similarity.py
tracktotrip4/smooth.py
tracktotrip4/spatiotemporal_segmentation.py
tracktotrip4/track.py
tracktotrip4/transportation_mode.py
tracktotrip4/utils.py
tracktotrip4-0.1.3.data/scripts/tracktotrip_geolife_dataset
tracktotrip4-0.1.3.data/scripts/tracktotrip_util
tracktotrip4-0.1.3.dist-info/METADATA
tracktotrip4-0.1.3.dist-info/WHEEL
tracktotrip4-0.1.3.dist-info/top_level.txt
tracktotrip4-0.1.3.dist-info/RECORD
