Metadata-Version: 2.4
Name: tracktotrip4
Version: 0.1.3
Summary: Track processing library for Python 3
Home-page: https://github.com/domiriel/tracktotrip4
Download-URL: https://github.com/domiriel/tracktotrip4/releases/tag/0.1.3
Author: Daniel Gonçalves, Daniel Serafim, Rui Gil
Author-email: dserafim1999@gmail.com
License: "MIT"
Keywords: track,trip,GPS,GPX
Requires-Dist: certifi==2025.1.31
Requires-Dist: changepy==0.4.0
Requires-Dist: charset-normalizer==3.4.1
Requires-Dist: gpxpy==1.6.2
Requires-Dist: idna==3.10
Requires-Dist: ikalman==0.2.0
Requires-Dist: joblib==1.4.2
Requires-Dist: numpy==2.2.4
Requires-Dist: requests==2.32.3
Requires-Dist: Rtree==1.4.0
Requires-Dist: rtreelib==0.2.0
Requires-Dist: scikit-learn==1.6.1
Requires-Dist: scipy==1.15.2
Requires-Dist: sklearn==0.0
Requires-Dist: threadpoolctl==3.6.0
Requires-Dist: urllib3==2.3.0
Dynamic: author
Dynamic: author-email
Dynamic: description
Dynamic: description-content-type
Dynamic: download-url
Dynamic: home-page
Dynamic: keywords
Dynamic: requires-dist
Dynamic: summary
